morphac/LICENSE
morphac/README.md
morphac/__init__.py
morphac/pytest.ini
morphac/run_examples.py
morphac/run_tests.py
morphac/version.py
morphac/constants/__init__.py
morphac/constants/_binding_constants_python.cpython-36m-x86_64-linux-gnu.so
morphac/constants/_binding_constants_python.cpython-37m-x86_64-linux-gnu.so
morphac/constants/_binding_constants_python.cpython-38-x86_64-linux-gnu.so
morphac/constants/colors.py
morphac/constants/environment_constants/__init__.py
morphac/constants/mechanics_constants/__init__.py
morphac/constructs/__init__.py
morphac/constructs/_binding_constructs_python.cpython-36m-x86_64-linux-gnu.so
morphac/constructs/_binding_constructs_python.cpython-37m-x86_64-linux-gnu.so
morphac/constructs/_binding_constructs_python.cpython-38-x86_64-linux-gnu.so
morphac/controllers/__init__.py
morphac/controllers/base/__init__.py
morphac/controllers/base/_binding_controllers_base_python.cpython-36m-x86_64-linux-gnu.so
morphac/controllers/base/_binding_controllers_base_python.cpython-37m-x86_64-linux-gnu.so
morphac/controllers/base/_binding_controllers_base_python.cpython-38-x86_64-linux-gnu.so
morphac/controllers/basic/__init__.py
morphac/controllers/basic/_binding_controllers_basic_python.cpython-36m-x86_64-linux-gnu.so
morphac/controllers/basic/_binding_controllers_basic_python.cpython-37m-x86_64-linux-gnu.so
morphac/controllers/basic/_binding_controllers_basic_python.cpython-38-x86_64-linux-gnu.so
morphac/environment/__init__.py
morphac/environment/_binding_environment_python.cpython-36m-x86_64-linux-gnu.so
morphac/environment/_binding_environment_python.cpython-37m-x86_64-linux-gnu.so
morphac/environment/_binding_environment_python.cpython-38-x86_64-linux-gnu.so
morphac/examples/__init__.py
morphac/examples/constant_controller_example.py
morphac/math/__init__.py
morphac/math/geometry/__init__.py
morphac/math/geometry/_binding_geometry_python.cpython-36m-x86_64-linux-gnu.so
morphac-0.1.0a1.dist-info/METADATA
morphac-0.1.0a1.dist-info/WHEEL
morphac-0.1.0a1.dist-info/top_level.txt
morphac-0.1.0a1.dist-info/RECORD
