Metadata-Version: 2.1
Name: morphac
Version: 0.1.0a1
Summary: Morphac is a planning and control library for mobile robots.
Home-page: https://github.com/shrenikm/Morphac
Author: Shrenik
Author-email: shrenik95@gmail.com
License: MIT
Keywords: robotics mobile_robots motion_planning planning control
Platform: UNKNOWN
Classifier: Development Status :: 3 - Alpha
Classifier: Intended Audience :: Science/Research
Classifier: License :: OSI Approved :: MIT License
Classifier: Natural Language :: English
Classifier: Operating System :: POSIX :: Linux
Classifier: Programming Language :: C++
Classifier: Programming Language :: Python :: 3.6
Classifier: Programming Language :: Python :: 3.7
Classifier: Programming Language :: Python :: 3.8
Classifier: Topic :: Scientific/Engineering
Classifier: Topic :: Scientific/Engineering :: Artificial Intelligence
Requires-Python: >=3.6
Requires-Dist: attrs (==20.2.0)
Requires-Dist: msgpack (==1.0.0)
Requires-Dist: numpy (==1.19.2)
Requires-Dist: opencv-python (==4.4.0.42)
Requires-Dist: pytest (==6.0.2)
